{
  "v": "5.4.1",
  "fr": 29.9700012207031,
  "ip": 0,
  "op": 156.00000635401,
  "w": 1500,
  "h": 1500,
  "nm": "Comp 1",
  "ddd": 0,
  "assets": [],
  "layers": [
    {
      "ddd": 0,
      "ind": 1,
      "ty": 4,
      "nm": "Cog Assets Outlines",
      "sr": 1,
      "ks": {
        "o": { "a": 0, "k": 100, "ix": 11 },
        "r": { "a": 0, "k": 0, "ix": 10 },
        "p": { "a": 0, "k": [752, 761, 0], "ix": 2 },
        "a": { "a": 0, "k": [447.124, 444.161, 0], "ix": 1 },
        "s": { "a": 0, "k": [100, 100, 100], "ix": 6 }
      },
      "ao": 0,
      "shapes": [
        {
          "ty": "gr",
          "it": [
            {
              "ind": 0,
              "ty": "sh",
              "ix": 1,
              "ks": {
                "a": 0,
                "k": {
                  "i": [
                    [102.727, 30.164],
                    [30.164, -102.727],
                    [-4.27, -27.357],
                    [0, 0],
                    [-5.669, 19.307],
                    [-75.871, -22.279],
                    [22.278, -75.87],
                    [51.019, -9.835],
                    [0, 0],
                    [-20.798, 70.831]
                  ],
                  "o": [
                    [-102.721, -30.161],
                    [-8.31, 28.301],
                    [0, 0],
                    [-2.303, -18.796],
                    [22.277, -75.869],
                    [75.871, 22.278],
                    [-15.63, 53.234],
                    [0, 0],
                    [67.551, -14.337],
                    [30.164, -102.726]
                  ],
                  "v": [
                    [44.495, -172.919],
                    [-196.339, -41.417],
                    [-201.89, 42.932],
                    [-152.43, 30.526],
                    [-147.676, -27.129],
                    [30.207, -124.265],
                    [127.335, 53.623],
                    [16.762, 153.965],
                    [29.862, 203.079],
                    [175.997, 67.911]
                  ],
                  "c": true
                },
                "ix": 2
              },
              "nm": "Path 1",
              "mn": "ADBE Vector Shape - Group",
              "hd": false
            },
            {
              "ty": "fl",
              "c": {
                "a": 0,
                "k": [0.238509398816, 0.479422625373, 0.715621888404, 1],
                "ix": 4
              },
              "o": { "a": 0, "k": 100, "ix": 5 },
              "r": 1,
              "nm": "Fill 1",
              "mn": "ADBE Vector Graphic - Fill",
              "hd": false
            },
            {
              "ty": "tr",
              "p": { "a": 0, "k": [447.084, 444.195], "ix": 2 },
              "a": { "a": 0, "k": [-8.5, 11.938], "ix": 1 },
              "s": { "a": 0, "k": [100, 100], "ix": 3 },
              "r": {
                "a": 1,
                "k": [
                  {
                    "i": { "x": [0.47], "y": [1] },
                    "o": { "x": [0.333], "y": [0] },
                    "n": ["0p47_1_0p333_0"],
                    "t": 7,
                    "s": [0],
                    "e": [-360]
                  },
                  { "t": 143.000005824509 }
                ],
                "ix": 6
              },
              "o": { "a": 0, "k": 100, "ix": 7 },
              "sk": { "a": 0, "k": 0, "ix": 4 },
              "sa": { "a": 0, "k": 0, "ix": 5 },
              "nm": "Transform"
            }
          ],
          "nm": "Group 1",
          "np": 2,
          "cix": 2,
          "ix": 1,
          "mn": "ADBE Vector Group",
          "hd": false
        },
        {
          "ty": "gr",
          "it": [
            {
              "ind": 0,
              "ty": "sh",
              "ix": 1,
              "ks": {
                "a": 0,
                "k": {
                  "i": [
                    [24.507, 11.889],
                    [0, 0],
                    [4.404, 21.652],
                    [0, 0],
                    [13.16, 23.831],
                    [0, 0],
                    [14.24, 4.181],
                    [10.918, -3.848],
                    [0, 0],
                    [19.233, 12.501],
                    [0, 0],
                    [26.125, 7.671],
                    [0, 0],
                    [11.895, -24.505],
                    [0, 0],
                    [21.698, -4.594],
                    [0, 0],
                    [11.176, 3.282],
                    [12.874, -7.185],
                    [0, 0],
                    [-8.899, -25.715],
                    [0, 0],
                    [12.107, -18.573],
                    [0, 0],
                    [7.674, -26.133],
                    [0, 0],
                    [-24.505, -11.896],
                    [0, 0],
                    [0, 0],
                    [0, 0],
                    [-0.688, 2.34],
                    [0, 0],
                    [-2.447, -0.325],
                    [0, 0],
                    [-5.101, 8.682],
                    [-20.81, 19.536],
                    [3.31, 9.395],
                    [0, 0],
                    [-2.095, 1.142],
                    [0, 0],
                    [-0.897, -0.263],
                    [-0.562, -0.75],
                    [0, 0],
                    [-9.719, 2.432],
                    [-28.505, -0.933],
                    [-4.369, 8.897],
                    [0, 0],
                    [-2.34, -0.687],
                    [0, 0],
                    [0.329, -2.455],
                    [0, 0],
                    [-8.685, -5.092],
                    [-19.976, -21.331],
                    [-9.571, 3.258],
                    [0, 0],
                    [-0.897, -0.263],
                    [-0.889, -1.627],
                    [0, 0],
                    [1.842, -1.62],
                    [0, 0],
                    [-2.433, -9.717],
                    [0.925, -28.51],
                    [-8.947, -4.197],
                    [0, 0],
                    [0.688, -2.341],
                    [0, 0],
                    [0, 0],
                    [2.447, 0.327],
                    [0, 0],
                    [5.041, -8.509],
                    [20.985, -19.483],
                    [-3.25, -9.565],
                    [0, 0],
                    [2.096, -1.153],
                    [0, 0],
                    [0.907, 0.267],
                    [0.564, 0.748],
                    [0, 0],
                    [0, 0],
                    [0, 0],
                    [-11.167, -3.28],
                    [-13.058, 7.128],
                    [0, 0],
                    [8.891, 25.715],
                    [0, 0],
                    [-12.051, 18.389],
                    [0, 0],
                    [-7.675, 26.136],
                    [0, 0]
                  ],
                  "o": [
                    [0, 0],
                    [-0.328, -22.215],
                    [0, 0],
                    [21.379, -16.825],
                    [0, 0],
                    [-7.129, -13.056],
                    [-11.167, -3.279],
                    [0, 0],
                    [-16.446, -15.992],
                    [0, 0],
                    [3.239, -27.047],
                    [0, 0],
                    [-26.136, -7.674],
                    [0, 0],
                    [-22.04, 0.382],
                    [0, 0],
                    [-7.106, -9.131],
                    [-14.237, -4.181],
                    [0, 0],
                    [-23.783, 12.986],
                    [0, 0],
                    [-15.471, 16.009],
                    [0, 0],
                    [-27.047, -3.239],
                    [0, 0],
                    [-7.672, 26.127],
                    [0, 0],
                    [0, 0],
                    [0, 0],
                    [-2.234, -1.048],
                    [0, 0],
                    [0.69, -2.35],
                    [0, 0],
                    [10.034, 1.177],
                    [14.442, -24.54],
                    [7.3, -6.862],
                    [0, 0],
                    [-0.739, -2.174],
                    [0, 0],
                    [1.638, -0.896],
                    [1.083, 0.318],
                    [0, 0],
                    [6.288, 7.918],
                    [27.559, -7.172],
                    [9.928, 0.172],
                    [0, 0],
                    [1.05, -2.244],
                    [0, 0],
                    [2.341, 0.688],
                    [0, 0],
                    [-1.183, 10.023],
                    [25.2, 14.836],
                    [6.858, 7.301],
                    [0, 0],
                    [1.059, -0.281],
                    [0.723, 0.212],
                    [0, 0],
                    [1.139, 2.104],
                    [0, 0],
                    [-7.862, 6.111],
                    [7.129, 27.739],
                    [-0.411, 10.058],
                    [0, 0],
                    [2.235, 1.048],
                    [0, 0],
                    [0, 0],
                    [-0.687, 2.341],
                    [0, 0],
                    [-10.022, -1.184],
                    [-14.626, 24.476],
                    [-7.301, 6.86],
                    [0, 0],
                    [0.727, 2.173],
                    [0, 0],
                    [-1.637, 0.884],
                    [-1.073, -0.314],
                    [0, 0],
                    [0, 0],
                    [0, 0],
                    [7.106, 9.132],
                    [14.239, 4.18],
                    [0, 0],
                    [23.78, -12.984],
                    [0, 0],
                    [15.471, -16.006],
                    [0, 0],
                    [27.044, 3.248],
                    [0, 0],
                    [8.036, -26.03]
                  ],
                  "v": [
                    [413.963, 35.542],
                    [356.429, 7.485],
                    [349.35, -58.406],
                    [399.692, -97.851],
                    [414.089, -168.207],
                    [376.154, -237.682],
                    [343.085, -264.425],
                    [309.358, -263.555],
                    [248.782, -242.584],
                    [195.226, -285.522],
                    [202.702, -348.314],
                    [163.152, -408.284],
                    [87.28, -430.562],
                    [21.578, -401.497],
                    [-6.86, -343.292],
                    [-72.682, -335.799],
                    [-111.762, -386.043],
                    [-139.855, -405.054],
                    [-182.123, -400.432],
                    [-251.779, -362.552],
                    [-277.707, -295.579],
                    [-256.533, -234.354],
                    [-297.809, -182.459],
                    [-360.598, -189.943],
                    [-420.57, -150.385],
                    [-442.849, -74.512],
                    [-413.781, -8.819],
                    [-359.098, 17.908],
                    [-344.61, -31.433],
                    [-391.602, -54.38],
                    [-394.185, -60.223],
                    [-371.906, -136.095],
                    [-366.571, -139.623],
                    [-287.718, -130.165],
                    [-262.778, -142.418],
                    [-209.733, -209.065],
                    [-203.273, -235.749],
                    [-229.622, -312.001],
                    [-227.288, -317.966],
                    [-157.813, -355.902],
                    [-153.967, -356.341],
                    [-151.522, -354.647],
                    [-102.367, -292.06],
                    [-76.013, -283.144],
                    [8.633, -292.738],
                    [32.186, -306.967],
                    [67.55, -379.388],
                    [73.396, -381.98],
                    [149.278, -359.699],
                    [152.794, -354.357],
                    [143.344, -275.501],
                    [155.6, -250.57],
                    [223.601, -196.144],
                    [250.407, -189.448],
                    [325.708, -215.885],
                    [328.675, -215.998],
                    [331.675, -213.551],
                    [369.611, -144.076],
                    [368.355, -137.782],
                    [305.475, -88.322],
                    [296.615, -62.145],
                    [305.805, 22.576],
                    [320.022, 46.126],
                    [391.961, 81.147],
                    [394.553, 87.004],
                    [372.276, 162.874],
                    [372.091, 162.819],
                    [366.756, 166.338],
                    [287.354, 156.73],
                    [262.65, 168.862],
                    [209.124, 235.165],
                    [202.419, 261.967],
                    [228.522, 337.755],
                    [226.185, 343.732],
                    [156.71, 381.668],
                    [152.857, 382.092],
                    [150.418, 380.403],
                    [108.774, 327.458],
                    [71.095, 361.223],
                    [110.539, 411.561],
                    [138.619, 430.581],
                    [180.896, 425.961],
                    [250.371, 388.025],
                    [276.295, 321.051],
                    [255.327, 260.469],
                    [296.907, 208.866],
                    [360.421, 216.553],
                    [420.392, 177.002],
                    [442.669, 101.131]
                  ],
                  "c": true
                },
                "ix": 2
              },
              "nm": "Path 1",
              "mn": "ADBE Vector Shape - Group",
              "hd": false
            },
            {
              "ty": "fl",
              "c": {
                "a": 0,
                "k": [0.238509398816, 0.479422625373, 0.715621888404, 1],
                "ix": 4
              },
              "o": { "a": 0, "k": 100, "ix": 5 },
              "r": 1,
              "nm": "Fill 1",
              "mn": "ADBE Vector Graphic - Fill",
              "hd": false
            },
            {
              "ty": "tr",
              "p": { "a": 0, "k": [445.124, 433.161], "ix": 2 },
              "a": { "a": 0, "k": [0, 0], "ix": 1 },
              "s": { "a": 0, "k": [100, 100], "ix": 3 },
              "r": {
                "a": 1,
                "k": [
                  {
                    "i": { "x": [0.468], "y": [1] },
                    "o": { "x": [0.333], "y": [0] },
                    "n": ["0p468_1_0p333_0"],
                    "t": 0,
                    "s": [0],
                    "e": [360]
                  },
                  { "t": 129.000005254278 }
                ],
                "ix": 6
              },
              "o": { "a": 0, "k": 100, "ix": 7 },
              "sk": { "a": 0, "k": 0, "ix": 4 },
              "sa": { "a": 0, "k": 0, "ix": 5 },
              "nm": "Transform"
            }
          ],
          "nm": "Group 2",
          "np": 4,
          "cix": 2,
          "ix": 2,
          "mn": "ADBE Vector Group",
          "hd": false
        }
      ],
      "ip": 0,
      "op": 900.000036657751,
      "st": 0,
      "bm": 0
    }
  ],
  "markers": []
}
